licensize
