Metadata-Version: 1.0
Name: licensize
Version: 0.1.2
Summary: Little tool that adds a FOSS licenses to your directory.
Home-page: http://bitbucket.com/michaelb/licensize/
Author: michaelb
Author-email: michaelpb@gmail.com
License: LGPL 3.0
Platform: UNKNOWN
